boofoo/__init__.py
boofoo/boofoo.py
boofoo-1.6.dist-info/LICENSE.txt
boofoo-1.6.dist-info/METADATA
boofoo-1.6.dist-info/WHEEL
boofoo-1.6.dist-info/entry_points.txt
boofoo-1.6.dist-info/top_level.txt
boofoo-1.6.dist-info/RECORD
