Metadata-Version: 2.1
Name: boofoo
Version: 1.6
Summary: Get cli commands
Home-page: https://github.com/naifalshaye/boofoo
Author: Naif Alshaye
Author-email: naif@naif.io
Project-URL: Bug Tracker, https://github.com/naifalshaye/boofoo/issues
Project-URL: repository, https://github.com/naifalshaye/boofoo
Classifier: Programming Language :: Python :: 3
Classifier: License :: OSI Approved :: MIT License
Classifier: Operating System :: OS Independent
Requires-Python: >=3.6
License-File: LICENSE.txt
Requires-Dist: docopt
Requires-Dist: openai
Requires-Dist: pyperclip
Requires-Dist: configparser
